nsubooking/__init__.py
nsubooking/app.py
nsubooking/configure.py
nsubooking/driver.py
nsubooking/event.py
nsubooking/logger.py
nsubooking/loop.py
nsubooking/settings.py
nsubooking-1.1.dist-info/METADATA
nsubooking-1.1.dist-info/WHEEL
nsubooking-1.1.dist-info/licenses/LICENSE
nsubooking-1.1.dist-info/RECORD
