Metadata-Version: 2.3
Name: nsubooking
Version: 1.1
Summary: Automatic booking of washing machines at NSU. 
Project-URL: Homepage, https://github.com/InfaNaSotku/NSUAutomaticBooking
Project-URL: Issues, https://github.com/InfaNaSotku/NSUAutomaticBooking/issues
Author-email: Maxim Gerasimov <infanasotku@gmail.com>
License-File: LICENSE
Classifier: License :: OSI Approved :: MIT License
Classifier: Operating System :: OS Independent
Classifier: Programming Language :: Python :: 3.11
Requires-Python: >=3.11
Requires-Dist: pydantic
Requires-Dist: pydantic-settings
Requires-Dist: selenium
